icon_plugin_spec/__init__.py
icon_plugin_spec/plugin_spec.py
icon_plugin_spec/tests/__init__.py
icon_plugin_spec/tests/test_komandPluginSpec.py
insightconnect_integrations_plugin_spec_tooling-1.3.2.dist-info/LICENSE
insightconnect_integrations_plugin_spec_tooling-1.3.2.dist-info/METADATA
insightconnect_integrations_plugin_spec_tooling-1.3.2.dist-info/WHEEL
insightconnect_integrations_plugin_spec_tooling-1.3.2.dist-info/top_level.txt
insightconnect_integrations_plugin_spec_tooling-1.3.2.dist-info/RECORD
