Metadata-Version: 2.1
Name: insightconnect-integrations-plugin-spec-tooling
Version: 1.3.2
Summary: Plugin spec parser tooling for InsightConnect integrations
Home-page: https://github.com/rapid7/icon-integrations-plugin-spec
Author: Rapid7 Integrations Alliance
Author-email: integrationsalliance@rapid7.com
License: MIT
Classifier: Programming Language :: Python :: 3
Classifier: Operating System :: OS Independent
License-File: LICENSE
Requires-Dist: PyYAML ==6.0.1
